[
    {
        "_id": "5d421b15fc13ae6520000000",
        "name": "Solarbreeze",
        "createdAt": "2019-01-23T17:47:30Z"
    },
    {
        "_id": "5d421b15fc13ae6520000001",
        "name": "Asoka",
        "createdAt": "2018-12-17T08:03:41Z"
    },
    {
        "_id": "5d421b15fc13ae6520000002",
        "name": "Lotstring",
        "createdAt": "2019-01-27T00:15:45Z"
    },
    {
        "_id": "5d421b15fc13ae6520000003",
        "name": "Cookley",
        "createdAt": "2018-07-19T02:51:43Z"
    },
    {
        "_id": "5d421b15fc13ae6520000004",
        "name": "Trippledex",
        "createdAt": "2018-08-24T17:30:26Z"
    },
    {
        "_id": "5d421b15fc13ae6520000005",
        "name": "Quo Lux",
        "createdAt": "2018-12-15T12:00:14Z"
    },
    {
        "_id": "5d421b15fc13ae6520000006",
        "name": "Andalax",
        "createdAt": "2018-05-23T22:28:29Z"
    },
    {
        "_id": "5d421b15fc13ae6520000007",
        "name": "Wrapsafe",
        "createdAt": "2018-09-30T03:57:48Z"
    },
    {
        "_id": "5d421b15fc13ae6520000008",
        "name": "Redhold",
        "createdAt": "2018-08-18T10:04:40Z"
    },
    {
        "_id": "5d421b15fc13ae6520000009",
        "name": "Treeflex",
        "createdAt": "2019-01-06T14:16:30Z"
    },
    {
        "_id": "5d421b15fc13ae652000000a",
        "name": "Duobam",
        "createdAt": "2019-03-23T12:35:58Z"
    },
    {
        "_id": "5d421b15fc13ae652000000b",
        "name": "Subin",
        "createdAt": "2018-11-18T21:33:05Z"
    },
    {
        "_id": "5d421b15fc13ae652000000c",
        "name": "Lotlux",
        "createdAt": "2018-05-31T22:11:29Z"
    },
    {
        "_id": "5d421b15fc13ae652000000d",
        "name": "Viva",
        "createdAt": "2018-09-13T21:24:19Z"
    },
    {
        "_id": "5d421b15fc13ae652000000e",
        "name": "Wrapsafe",
        "createdAt": "2018-08-24T12:00:10Z"
    },
    {
        "_id": "5d421b15fc13ae652000000f",
        "name": "Namfix",
        "createdAt": "2018-10-09T11:26:37Z"
    },
    {
        "_id": "5d421b15fc13ae6520000010",
        "name": "Latlux",
        "createdAt": "2019-05-07T01:31:07Z"
    },
    {
        "_id": "5d421b15fc13ae6520000011",
        "name": "It",
        "createdAt": "2019-04-07T00:13:26Z"
    },
    {
        "_id": "5d421b15fc13ae6520000012",
        "name": "Overhold",
        "createdAt": "2018-09-29T04:39:18Z"
    },
    {
        "_id": "5d421b15fc13ae6520000013",
        "name": "Zoolab",
        "createdAt": "2019-05-14T15:56:41Z"
    },
    {
        "_id": "5d421b15fc13ae6520000014",
        "name": "Bamity",
        "createdAt": "2018-11-21T09:04:32Z"
    },
    {
        "_id": "5d421b15fc13ae6520000015",
        "name": "Lotstring",
        "createdAt": "2019-04-23T10:53:21Z"
    },
    {
        "_id": "5d421b15fc13ae6520000016",
        "name": "Biodex",
        "createdAt": "2019-04-20T02:46:30Z"
    },
    {
        "_id": "5d421b15fc13ae6520000017",
        "name": "Gembucket",
        "createdAt": "2019-05-17T14:16:04Z"
    },
    {
        "_id": "5d421b15fc13ae6520000018",
        "name": "Bamity",
        "createdAt": "2018-08-04T04:12:39Z"
    },
    {
        "_id": "5d421b15fc13ae6520000019",
        "name": "Tin",
        "createdAt": "2018-10-23T18:31:10Z"
    },
    {
        "_id": "5d421b15fc13ae652000001a",
        "name": "Overhold",
        "createdAt": "2019-01-10T08:09:41Z"
    },
    {
        "_id": "5d421b15fc13ae652000001b",
        "name": "Stim",
        "createdAt": "2019-04-18T16:29:36Z"
    },
    {
        "_id": "5d421b15fc13ae652000001c",
        "name": "Biodex",
        "createdAt": "2018-06-06T08:14:04Z"
    },
    {
        "_id": "5d421b15fc13ae652000001d",
        "name": "Aerified",
        "createdAt": "2018-12-02T17:51:50Z"
    },
    {
        "_id": "5d421b15fc13ae652000001e",
        "name": "Lotstring",
        "createdAt": "2018-07-05T03:39:57Z"
    },
    {
        "_id": "5d421b15fc13ae652000001f",
        "name": "Zathin",
        "createdAt": "2019-05-10T04:18:25Z"
    },
    {
        "_id": "5d421b15fc13ae6520000020",
        "name": "Voyatouch",
        "createdAt": "2018-09-14T17:43:58Z"
    },
    {
        "_id": "5d421b15fc13ae6520000021",
        "name": "Lotstring",
        "createdAt": "2019-02-03T04:49:43Z"
    },
    {
        "_id": "5d421b15fc13ae6520000022",
        "name": "Lotlux",
        "createdAt": "2018-09-24T01:28:10Z"
    },
    {
        "_id": "5d421b15fc13ae6520000023",
        "name": "Bitchip",
        "createdAt": "2018-08-10T12:53:21Z"
    },
    {
        "_id": "5d421b15fc13ae6520000024",
        "name": "Latlux",
        "createdAt": "2018-08-17T21:55:29Z"
    },
    {
        "_id": "5d421b15fc13ae6520000025",
        "name": "Asoka",
        "createdAt": "2018-10-12T07:31:44Z"
    },
    {
        "_id": "5d421b15fc13ae6520000026",
        "name": "Cardify",
        "createdAt": "2019-05-15T19:23:21Z"
    },
    {
        "_id": "5d421b15fc13ae6520000027",
        "name": "Keylex",
        "createdAt": "2018-07-25T10:06:05Z"
    },
    {
        "_id": "5d421b15fc13ae6520000028",
        "name": "It",
        "createdAt": "2019-01-27T22:54:52Z"
    },
    {
        "_id": "5d421b15fc13ae6520000029",
        "name": "Duobam",
        "createdAt": "2018-07-10T09:46:27Z"
    },
    {
        "_id": "5d421b15fc13ae652000002a",
        "name": "Andalax",
        "createdAt": "2018-08-10T18:45:03Z"
    },
    {
        "_id": "5d421b15fc13ae652000002b",
        "name": "Vagram",
        "createdAt": "2018-09-27T01:39:25Z"
    },
    {
        "_id": "5d421b15fc13ae652000002c",
        "name": "Trippledex",
        "createdAt": "2018-12-12T22:35:02Z"
    },
    {
        "_id": "5d421b15fc13ae652000002d",
        "name": "Tresom",
        "createdAt": "2018-07-22T05:34:40Z"
    },
    {
        "_id": "5d421b15fc13ae652000002e",
        "name": "Wrapsafe",
        "createdAt": "2018-09-10T21:05:07Z"
    },
    {
        "_id": "5d421b15fc13ae652000002f",
        "name": "Daltfresh",
        "createdAt": "2018-10-23T17:16:25Z"
    },
    {
        "_id": "5d421b15fc13ae6520000030",
        "name": "Latlux",
        "createdAt": "2018-08-27T22:54:56Z"
    },
    {
        "_id": "5d421b15fc13ae6520000031",
        "name": "Flexidy",
        "createdAt": "2018-07-14T14:25:17Z"
    },
    {
        "_id": "5d421b15fc13ae6520000032",
        "name": "Tin",
        "createdAt": "2018-11-08T18:01:30Z"
    },
    {
        "_id": "5d421b15fc13ae6520000033",
        "name": "Lotlux",
        "createdAt": "2018-06-04T00:22:43Z"
    },
    {
        "_id": "5d421b15fc13ae6520000034",
        "name": "Prodder",
        "createdAt": "2019-02-24T23:01:39Z"
    },
    {
        "_id": "5d421b15fc13ae6520000035",
        "name": "Veribet",
        "createdAt": "2018-08-07T04:49:06Z"
    },
    {
        "_id": "5d421b15fc13ae6520000036",
        "name": "Rank",
        "createdAt": "2018-05-21T09:44:46Z"
    },
    {
        "_id": "5d421b15fc13ae6520000037",
        "name": "Domainer",
        "createdAt": "2019-05-11T00:28:04Z"
    },
    {
        "_id": "5d421b15fc13ae6520000038",
        "name": "Span",
        "createdAt": "2018-12-08T00:29:40Z"
    },
    {
        "_id": "5d421b15fc13ae6520000039",
        "name": "Solarbreeze",
        "createdAt": "2019-03-25T09:01:48Z"
    },
    {
        "_id": "5d421b15fc13ae652000003a",
        "name": "Flowdesk",
        "createdAt": "2018-06-19T23:04:36Z"
    },
    {
        "_id": "5d421b15fc13ae652000003b",
        "name": "Bitchip",
        "createdAt": "2019-05-16T14:56:44Z"
    },
    {
        "_id": "5d421b15fc13ae652000003c",
        "name": "Y-Solowarm",
        "createdAt": "2018-10-12T18:52:54Z"
    },
    {
        "_id": "5d421b15fc13ae652000003d",
        "name": "Matsoft",
        "createdAt": "2018-12-07T11:02:09Z"
    },
    {
        "_id": "5d421b15fc13ae652000003e",
        "name": "Namfix",
        "createdAt": "2018-10-04T19:29:04Z"
    },
    {
        "_id": "5d421b15fc13ae652000003f",
        "name": "Quo Lux",
        "createdAt": "2018-08-07T05:39:42Z"
    },
    {
        "_id": "5d421b15fc13ae6520000040",
        "name": "Lotstring",
        "createdAt": "2019-02-02T21:11:35Z"
    },
    {
        "_id": "5d421b15fc13ae6520000041",
        "name": "Mat Lam Tam",
        "createdAt": "2018-12-19T23:43:03Z"
    },
    {
        "_id": "5d421b15fc13ae6520000042",
        "name": "Voltsillam",
        "createdAt": "2018-08-24T19:37:52Z"
    },
    {
        "_id": "5d421b15fc13ae6520000043",
        "name": "Lotlux",
        "createdAt": "2018-11-16T18:07:59Z"
    },
    {
        "_id": "5d421b15fc13ae6520000044",
        "name": "Fixflex",
        "createdAt": "2018-11-06T20:18:03Z"
    },
    {
        "_id": "5d421b15fc13ae6520000045",
        "name": "Greenlam",
        "createdAt": "2018-10-26T00:40:41Z"
    },
    {
        "_id": "5d421b15fc13ae6520000046",
        "name": "Transcof",
        "createdAt": "2018-07-07T05:28:19Z"
    },
    {
        "_id": "5d421b15fc13ae6520000047",
        "name": "Toughjoyfax",
        "createdAt": "2019-01-23T17:27:35Z"
    },
    {
        "_id": "5d421b15fc13ae6520000048",
        "name": "Zoolab",
        "createdAt": "2018-07-27T08:36:37Z"
    },
    {
        "_id": "5d421b15fc13ae6520000049",
        "name": "Veribet",
        "createdAt": "2018-11-23T22:53:46Z"
    },
    {
        "_id": "5d421b15fc13ae652000004a",
        "name": "Redhold",
        "createdAt": "2019-05-17T04:36:31Z"
    },
    {
        "_id": "5d421b15fc13ae652000004b",
        "name": "Vagram",
        "createdAt": "2018-11-18T13:18:25Z"
    },
    {
        "_id": "5d421b15fc13ae652000004c",
        "name": "Domainer",
        "createdAt": "2018-10-30T16:41:11Z"
    },
    {
        "_id": "5d421b15fc13ae652000004d",
        "name": "Namfix",
        "createdAt": "2019-01-19T15:11:21Z"
    },
    {
        "_id": "5d421b15fc13ae652000004e",
        "name": "Greenlam",
        "createdAt": "2019-03-24T06:06:37Z"
    },
    {
        "_id": "5d421b15fc13ae652000004f",
        "name": "Bytecard",
        "createdAt": "2018-09-01T16:40:04Z"
    },
    {
        "_id": "5d421b15fc13ae6520000050",
        "name": "Asoka",
        "createdAt": "2019-02-07T09:03:00Z"
    },
    {
        "_id": "5d421b15fc13ae6520000051",
        "name": "Greenlam",
        "createdAt": "2018-07-02T12:01:37Z"
    },
    {
        "_id": "5d421b15fc13ae6520000052",
        "name": "Daltfresh",
        "createdAt": "2018-11-07T05:54:34Z"
    },
    {
        "_id": "5d421b15fc13ae6520000053",
        "name": "Vagram",
        "createdAt": "2018-06-24T17:37:31Z"
    },
    {
        "_id": "5d421b15fc13ae6520000054",
        "name": "Voyatouch",
        "createdAt": "2019-03-07T20:46:09Z"
    },
    {
        "_id": "5d421b15fc13ae6520000055",
        "name": "Lotlux",
        "createdAt": "2018-12-02T07:20:41Z"
    },
    {
        "_id": "5d421b15fc13ae6520000056",
        "name": "Mat Lam Tam",
        "createdAt": "2018-10-21T07:55:53Z"
    },
    {
        "_id": "5d421b15fc13ae6520000057",
        "name": "Asoka",
        "createdAt": "2018-12-05T05:25:07Z"
    },
    {
        "_id": "5d421b15fc13ae6520000058",
        "name": "Y-Solowarm",
        "createdAt": "2018-11-18T20:19:44Z"
    },
    {
        "_id": "5d421b15fc13ae6520000059",
        "name": "Prodder",
        "createdAt": "2018-05-26T15:57:32Z"
    },
    {
        "_id": "5d421b15fc13ae652000005a",
        "name": "Cardguard",
        "createdAt": "2018-10-30T15:49:18Z"
    },
    {
        "_id": "5d421b15fc13ae652000005b",
        "name": "Transcof",
        "createdAt": "2018-07-09T18:05:23Z"
    },
    {
        "_id": "5d421b15fc13ae652000005c",
        "name": "Stringtough",
        "createdAt": "2018-10-12T21:48:22Z"
    },
    {
        "_id": "5d421b15fc13ae652000005d",
        "name": "Alphazap",
        "createdAt": "2019-02-03T16:11:09Z"
    },
    {
        "_id": "5d421b15fc13ae652000005e",
        "name": "Tres-Zap",
        "createdAt": "2018-06-09T01:05:38Z"
    },
    {
        "_id": "5d421b15fc13ae652000005f",
        "name": "Bitwolf",
        "createdAt": "2018-06-09T05:57:27Z"
    },
    {
        "_id": "5d421b15fc13ae6520000060",
        "name": "Temp",
        "createdAt": "2018-11-14T10:15:32Z"
    },
    {
        "_id": "5d421b15fc13ae6520000061",
        "name": "Transcof",
        "createdAt": "2018-05-29T07:02:18Z"
    },
    {
        "_id": "5d421b15fc13ae6520000062",
        "name": "Fix San",
        "createdAt": "2018-10-10T09:24:50Z"
    },
    {
        "_id": "5d421b15fc13ae6520000063",
        "name": "Zontrax",
        "createdAt": "2019-01-09T09:47:14Z"
    }
]